easyode/__init__.py
easyode-1.1.0.dist-info/METADATA
easyode-1.1.0.dist-info/WHEEL
easyode-1.1.0.dist-info/top_level.txt
easyode-1.1.0.dist-info/RECORD
